premark/__init__.py
premark/cli.py
premark/config.py
premark/default_config.yaml
premark/presentation.py
premark/section.py
premark/utils.py
premark/templates/default.css
premark/templates/default.html
Premark-0.1.3.dist-info/LICENSE
Premark-0.1.3.dist-info/METADATA
Premark-0.1.3.dist-info/WHEEL
Premark-0.1.3.dist-info/entry_points.txt
Premark-0.1.3.dist-info/top_level.txt
Premark-0.1.3.dist-info/RECORD
