Metadata-Version: 2.1
Name: Premark
Version: 0.1.3
Summary: Generate single-file HTML presentations from one or many markdown files, using Remark.js.
Home-page: https://github.com/eswan18/premark
Author: Ethan Swan
Author-email: ethanpswan@gmail.com
Project-URL: Bug Tracker, https://github.com/eswan18/premark/issues
Project-URL: Documentation, https://premark.readthedocs.io
Classifier: Programming Language :: Python :: 3
Classifier: License :: OSI Approved :: MIT License
Classifier: Operating System :: OS Independent
Requires-Python: >=3.9
License-File: LICENSE
Requires-Dist: click
Requires-Dist: jinja2
Requires-Dist: pyyaml
Provides-Extra: dev
Requires-Dist: flake8 ; extra == 'dev'
Requires-Dist: mypy ; extra == 'dev'
Requires-Dist: types-setuptools ; extra == 'dev'
Requires-Dist: types-PyYAML ; extra == 'dev'
Requires-Dist: pytest ; extra == 'dev'
Requires-Dist: pytest-cov ; extra == 'dev'
Requires-Dist: pytest-mock ; extra == 'dev'
Requires-Dist: tox ; extra == 'dev'
Requires-Dist: tox-pyenv ; extra == 'dev'
Requires-Dist: sphinx ; extra == 'dev'
Requires-Dist: sphinx-rtd-theme ; extra == 'dev'
Requires-Dist: myst-parser (>=0.12.7) ; extra == 'dev'
Requires-Dist: build ; extra == 'dev'
Requires-Dist: twine ; extra == 'dev'
Provides-Extra: docs
Requires-Dist: sphinx ; extra == 'docs'
Requires-Dist: sphinx-rtd-theme ; extra == 'docs'
Requires-Dist: myst-parser (>=0.12.7) ; extra == 'docs'
Provides-Extra: lint
Requires-Dist: flake8 ; extra == 'lint'
Provides-Extra: test
Requires-Dist: pytest ; extra == 'test'
Requires-Dist: pytest-cov ; extra == 'test'
Requires-Dist: pytest-mock ; extra == 'test'
Provides-Extra: tox
Requires-Dist: tox ; extra == 'tox'
Requires-Dist: tox-pyenv ; extra == 'tox'
Provides-Extra: typecheck
Requires-Dist: mypy ; extra == 'typecheck'
Requires-Dist: types-setuptools ; extra == 'typecheck'
Requires-Dist: types-PyYAML ; extra == 'typecheck'
